pycut_pursuit/__init__.py
pycut_pursuit/cp_d0_dist.py
pycut_pursuit/cp_d0_dist_cpy.cp313-win_amd64.pyd
pycut_pursuit/cp_d1_lsx.py
pycut_pursuit/cp_d1_lsx_cpy.cp313-win_amd64.pyd
pycut_pursuit/cp_d1_ql1b.py
pycut_pursuit/cp_d1_ql1b_cpy.cp313-win_amd64.pyd
pycut_pursuit/cp_prox_tv.py
pycut_pursuit/cp_prox_tv_cpy.cp313-win_amd64.pyd
pycut_pursuit-0.1.4.dist-info/licenses/LICENSE
pycut_pursuit-0.1.4.dist-info/METADATA
pycut_pursuit-0.1.4.dist-info/WHEEL
pycut_pursuit-0.1.4.dist-info/top_level.txt
pycut_pursuit-0.1.4.dist-info/RECORD
