Metadata-Version: 2.4
Name: pycut-pursuit
Version: 0.1.4
Summary: cut pursuit algorithms
Author-email: Hugo Raguet <hugo.raguet@insa-cvl.fr>, Loic Landrieu <loic.landrieu@enpc.fr>
Maintainer-email: Hugo Raguet <hugo.raguet@insa-cvl.fr>
License:                     GNU GENERAL PUBLIC LICENSE
Project-URL: homepage, https://gitlab.com/1a7r0ch3/parallel-cut-pursuit
Project-URL: repository, https://gitlab.com/1a7r0ch3/parallel-cut-pursuit
Keywords: point clouds,features,3D,LiDAR
Classifier: Development Status :: 3 - Alpha
Classifier: Programming Language :: Python
Classifier: Topic :: Scientific/Engineering
Requires-Python: >=3.9
License-File: LICENSE
Dynamic: license-file
